fastapi_query_conditions/__init__.py
fastapi_query_conditions-1.0.2.dist-info/LICENSE
fastapi_query_conditions-1.0.2.dist-info/METADATA
fastapi_query_conditions-1.0.2.dist-info/WHEEL
fastapi_query_conditions-1.0.2.dist-info/top_level.txt
fastapi_query_conditions-1.0.2.dist-info/RECORD
