Metadata-Version: 2.1
Name: fastapi-query-conditions
Version: 1.0.2
Summary: FastAPI-Query-Conditions is a dependency that parses a query string into conditions using operators enclosed in square brackets
Home-page: https://github.com/jonghwanhyeon/fastapi-query-conditions
Author: Jonghwan Hyeon
Author-email: jonghwanhyeon93@gmail.com
License: MIT
Keywords: fastapi,query,querystring,condition
Classifier: Development Status :: 4 - Beta
Classifier: License :: OSI Approved :: MIT License
Classifier: Programming Language :: Python :: 3
Classifier: Programming Language :: Python :: 3 :: Only
Requires-Python: >=3.7
License-File: LICENSE
Requires-Dist: fastapi
